ctabustracker/__init__.py
ctabustracker/bustracker.py
ctabustracker-0.2.dev2.dist-info/DESCRIPTION.rst
ctabustracker-0.2.dev2.dist-info/METADATA
ctabustracker-0.2.dev2.dist-info/RECORD
ctabustracker-0.2.dev2.dist-info/WHEEL
ctabustracker-0.2.dev2.dist-info/metadata.json
ctabustracker-0.2.dev2.dist-info/top_level.txt
