Metadata-Version: 2.0
Name: ctabustracker
Version: 0.2.dev2
Summary: A python wrapper for the Chicago Transit Authority's Bustracker API.
Home-page: https://github.com/tsaylor/ctabustracker
Author: Tim Saylor
Author-email: tim.saylor@gmail.com
License: MIT
Platform: UNKNOWN
Requires-Python: >=2.7, !=3.0.*, !=3.1.*, !=3.2.*, <4
Requires-Dist: beautifulsoup4
Requires-Dist: lxml
